bootstrapper/__init__.py
bootstrapper/bootstrapper.py
bootstrapper/data/.gitignore
bootstrapper/data/Makefile
bootstrapper/data/README.md
python_docs_bootstrapper-0.1.2.dist-info/LICENSE
python_docs_bootstrapper-0.1.2.dist-info/METADATA
python_docs_bootstrapper-0.1.2.dist-info/WHEEL
python_docs_bootstrapper-0.1.2.dist-info/entry_points.txt
python_docs_bootstrapper-0.1.2.dist-info/top_level.txt
python_docs_bootstrapper-0.1.2.dist-info/RECORD
