Metadata-Version: 2.1
Name: python-docs-bootstrapper
Version: 0.1.2
Summary: Bootstrapper for Python documentation translations
Author-email: egeakman <me@egeakman.dev>
License: MIT
Project-URL: Homepage, https://github.com/egeakman/python-docs-bootstrapper
Project-URL: Issues, https://github.com/egeakman/python-docs-bootstrapper/issues
Project-URL: Releases, https://github.com/egeakman/python-docs-bootstrapper/releases
Keywords: automation,CLI,documentation,i18n,python-docs,sphinx,translation,utilities
Classifier: Development Status :: 5 - Production/Stable
Classifier: Environment :: Console
Classifier: License :: OSI Approved :: MIT License
Classifier: Operating System :: MacOS :: MacOS X
Classifier: Operating System :: Microsoft :: Windows
Classifier: Operating System :: POSIX :: Linux
Classifier: Programming Language :: Python :: 3 :: Only
Classifier: Programming Language :: Python :: 3.10
Classifier: Programming Language :: Python :: 3.11
Classifier: Programming Language :: Python :: 3.12
Classifier: Topic :: Utilities
Requires-Python: >=3.10
License-File: LICENSE
Requires-Dist: sphinx ==4.5
